vlk/__init__.py
vlk/cli.py
vlkcli-0.1.0.dist-info/METADATA
vlkcli-0.1.0.dist-info/WHEEL
vlkcli-0.1.0.dist-info/entry_points.txt
vlkcli-0.1.0.dist-info/RECORD
