Metadata-Version: 2.1
Name: vlkcli
Version: 0.1.0
Summary: 
Author: Omar Ibañez
Author-email: jesus.ibanez@azumo.co
Requires-Python: >=3.9,<4.0
Classifier: Programming Language :: Python :: 3
Classifier: Programming Language :: Python :: 3.9
Classifier: Programming Language :: Python :: 3.10
Classifier: Programming Language :: Python :: 3.11
Classifier: Programming Language :: Python :: 3.12
Classifier: Programming Language :: Python :: 3.13
Requires-Dist: pyyaml (>=6.0.2,<6.1.0)
Requires-Dist: requests (>=2.32.3,<2.33.0)
